[
  {
    "TenantId": "00000000-0000-0000-0000-000000000000",
    "TimeGenerated": "5/11/2022, 6:31:37.177 PM",
    "SourceSystem": "OpsManager",
    "Account": "WORKGROUP\\EC2AMAZ-HK672QP$",
    "AccountType": "Machine",
    "Computer": "EC2AMAZ-HK672QP",
    "EventSourceName": "Microsoft-Windows-Security-Auditing",
    "Channel": "Security",
    "Task": 12804,
    "Level": 8,
    "EventData": "<EventData xmlns=\"http://schemas.microsoft.com/win/2004/08/events/event\">\n  <Data Name=\"SubjectUserSid\">S-1-5-20</Data>\n  <Data Name=\"SubjectUserName\">EC2AMAZ-HK672QP$</Data>\n  <Data Name=\"SubjectDomainName\">WORKGROUP</Data>\n  <Data Name=\"SubjectLogonId\">0x3e4</Data>\n  <Data Name=\"TaskName\">\\Microsoft\\Windows\\SoftwareProtectionPlatform\\SvcRestartTaskLogon</Data>\n  <Data Name=\"TaskContent\">&lt;?xml version=\"1.0\" encoding=\"UTF-16\"?&gt; &lt;Task xmlns=\"http://schemas.microsoft.com/windows/2004/02/mit/task\"&gt;   &lt;RegistrationInfo&gt;     &lt;Version&gt;1.0&lt;/Version&gt;     &lt;SecurityDescriptor&gt;D:P(A;;FA;;;SY)(A;;FA;;;BA)(A;;FRFW;;;S-1-5-80-123231216-2592883651-3715271367-3753151631-4175906628)(A;;FR;;;S-1-5-4)&lt;/SecurityDescriptor&gt;     &lt;Source&gt;$(@%systemroot%\\system32\\sppc.dll,-200)&lt;/Source&gt;     &lt;Author&gt;$(@%systemroot%\\system32\\sppc.dll,-200)&lt;/Author&gt;     &lt;Description&gt;$(@%systemroot%\\system32\\sppc.dll,-202)&lt;/Description&gt;     &lt;URI&gt;\\Microsoft\\Windows\\SoftwareProtectionPlatform\\SvcRestartTaskLogon&lt;/URI&gt;   &lt;/RegistrationInfo&gt;   &lt;Principals&gt;     &lt;Principal id=\"InteractiveUser\"&gt;       &lt;GroupId&gt;S-1-5-4&lt;/GroupId&gt;     &lt;/Principal&gt;   &lt;/Principals&gt;   &lt;Settings&gt;     &lt;AllowHardTerminate&gt;false&lt;/AllowHardTerminate&gt;     &lt;DisallowStartIfOnBatteries&gt;false&lt;/DisallowStartIfOnBatteries&gt;     &lt;StopIfGoingOnBatteries&gt;false&lt;/StopIfGoingOnBatteries&gt;     &lt;ExecutionTimeLimit&gt;PT0S&lt;/ExecutionTimeLimit&gt;     &lt;Hidden&gt;true&lt;/Hidden&gt;     &lt;MultipleInstancesPolicy&gt;IgnoreNew&lt;/MultipleInstancesPolicy&gt;     &lt;RestartOnFailure&gt;       &lt;Count&gt;3&lt;/Count&gt;       &lt;Interval&gt;PT1M&lt;/Interval&gt;     &lt;/RestartOnFailure&gt;     &lt;IdleSettings&gt;       &lt;StopOnIdleEnd&gt;true&lt;/StopOnIdleEnd&gt;       &lt;RestartOnIdle&gt;false&lt;/RestartOnIdle&gt;     &lt;/IdleSettings&gt;     &lt;UseUnifiedSchedulingEngine&gt;true&lt;/UseUnifiedSchedulingEngine&gt;   &lt;/Settings&gt;   &lt;Triggers&gt;     &lt;LogonTrigger /&gt;   &lt;/Triggers&gt;   &lt;Actions Context=\"InteractiveUser\"&gt;     &lt;ComHandler&gt;       &lt;ClassId&gt;{B1AEBB5D-EAD9-4476-B375-9C3ED9F32AFC}&lt;/ClassId&gt;       &lt;Data&gt;&lt;![CDATA[logon]]&gt;&lt;/Data&gt;     &lt;/ComHandler&gt;   &lt;/Actions&gt; &lt;/Task&gt;</Data>\n  <Data Name=\"ClientProcessStartKey\">106960491150526338</Data>\n  <Data Name=\"ClientProcessId\">12124</Data>\n  <Data Name=\"ParentProcessId\">752</Data>\n  <Data Name=\"RpcCallClientLocality\">0</Data>\n  <Data Name=\"FQDN\">EC2AMAZ-HK672QP</Data>\n</EventData>",
    "EventID": 4700,
    "Activity": "4700 - A scheduled task was enabled.",
    "SourceComputerId": "be71a2cf-5bbe-4000-8f3b-0f6fe60570e5",
    "EventOriginId": "00000000-0000-0000-0000-000000000000",
    "MG": "00000000-0000-0000-0000-000000000001",
    "TimeCollected": "5/11/2022, 6:31:49.698 PM",
    "ManagementGroupName": "AOI-00000000-0000-0000-0000-000000000000",
    "AccessList": "",
    "AccessMask": "",
    "AccessReason": "",
    "AccountDomain": "",
    "AccountExpires": "",
    "AccountName": "",
    "AccountSessionIdentifier": "",
    "AdditionalInfo": "",
    "AdditionalInfo2": "",
    "AllowedToDelegateTo": "",
    "Attributes": "",
    "AuditPolicyChanges": "",
    "AuditsDiscarded": "",
    "AuthenticationLevel": "",
    "AuthenticationPackageName": "",
    "AuthenticationProvider": "",
    "AuthenticationServer": "",
    "AuthenticationService": "",
    "AuthenticationType": "",
    "CACertificateHash": "",
    "CalledStationID": "",
    "CallerProcessId": "",
    "CallerProcessName": "",
    "CallingStationID": "",
    "CAPublicKeyHash": "",
    "CategoryId": "",
    "CertificateDatabaseHash": "",
    "ClassId": "",
    "ClassName": "",
    "ClientAddress": "",
    "ClientIPAddress": "",
    "ClientName": "",
    "CommandLine": "",
    "CompatibleIds": "",
    "DCDNSName": "",
    "DeviceDescription": "",
    "DeviceId": "",
    "DisplayName": "",
    "Disposition": "",
    "DomainBehaviorVersion": "",
    "DomainName": "",
    "DomainPolicyChanged": "",
    "DomainSid": "",
    "EAPType": "",
    "ElevatedToken": "",
    "ErrorCode": "",
    "ExtendedQuarantineState": "",
    "FailureReason": "",
    "FileHash": "",
    "FilePath": "",
    "FilePathNoUser": "",
    "Filter": "",
    "ForceLogoff": "",
    "Fqbn": "",
    "FullyQualifiedSubjectMachineName": "",
    "FullyQualifiedSubjectUserName": "",
    "GroupMembership": "",
    "HandleId": "",
    "HardwareIds": "",
    "HomeDirectory": "",
    "HomePath": "",
    "ImpersonationLevel": "",
    "InterfaceUuid": "",
    "IpAddress": "",
    "IpPort": "",
    "KeyLength": "",
    "LmPackageName": "",
    "LocationInformation": "",
    "LockoutDuration": "",
    "LockoutObservationWindow": "",
    "LockoutThreshold": "",
    "LoggingResult": "",
    "LogonGuid": "",
    "LogonHours": "",
    "LogonID": "",
    "LogonProcessName": "",
    "LogonType": "",
    "LogonTypeName": "",
    "MachineAccountQuota": "",
    "MachineInventory": "",
    "MachineLogon": "",
    "MandatoryLabel": "",
    "MaxPasswordAge": "",
    "MemberName": "",
    "MemberSid": "",
    "MinPasswordAge": "",
    "MinPasswordLength": "",
    "MixedDomainMode": "",
    "NASIdentifier": "",
    "NASIPv4Address": "",
    "NASIPv6Address": "",
    "NASPort": "",
    "NASPortType": "",
    "NetworkPolicyName": "",
    "NewDate": "",
    "NewMaxUsers": "",
    "NewProcessId": "",
    "NewProcessName": "",
    "NewRemark": "",
    "NewShareFlags": "",
    "NewTime": "",
    "NewUacValue": "",
    "NewValue": "",
    "NewValueType": "",
    "ObjectName": "",
    "ObjectServer": "",
    "ObjectType": "",
    "ObjectValueName": "",
    "OemInformation": "",
    "OldMaxUsers": "",
    "OldRemark": "",
    "OldShareFlags": "",
    "OldUacValue": "",
    "OldValue": "",
    "OldValueType": "",
    "OperationType": "",
    "PackageName": "",
    "ParentProcessName": "",
    "PasswordHistoryLength": "",
    "PasswordLastSet": "",
    "PasswordProperties": "",
    "PreviousDate": "",
    "PreviousTime": "",
    "PrimaryGroupId": "",
    "PrivateKeyUsageCount": "",
    "PrivilegeList": "",
    "Process": "",
    "ProcessId": "",
    "ProcessName": "",
    "Properties": "",
    "ProfilePath": "",
    "ProtocolSequence": "",
    "ProxyPolicyName": "",
    "QuarantineHelpURL": "",
    "QuarantineSessionID": "",
    "QuarantineSessionIdentifier": "",
    "QuarantineState": "",
    "QuarantineSystemHealthResult": "",
    "RelativeTargetName": "",
    "RemoteIpAddress": "",
    "RemotePort": "",
    "Requester": "",
    "RequestId": "",
    "RestrictedAdminMode": "",
    "RowsDeleted": "",
    "SamAccountName": "",
    "ScriptPath": "",
    "SecurityDescriptor": "",
    "ServiceAccount": "",
    "ServiceFileName": "",
    "ServiceName": "",
    "ServiceStartType": "",
    "ServiceType": "",
    "SessionName": "",
    "ShareLocalPath": "",
    "ShareName": "",
    "SidHistory": "",
    "Status": "",
    "SubjectAccount": "WORKGROUP\\EC2AMAZ-HK672QP$",
    "SubcategoryGuid": "",
    "SubcategoryId": "",
    "Subject": "",
    "SubjectDomainName": "WORKGROUP",
    "SubjectKeyIdentifier": "",
    "SubjectLogonId": "0x3e4",
    "SubjectMachineName": "",
    "SubjectMachineSID": "",
    "SubjectUserName": "EC2AMAZ-HK672QP$",
    "SubjectUserSid": "S-1-5-20",
    "SubStatus": "",
    "TableId": "",
    "TargetAccount": "",
    "TargetDomainName": "",
    "TargetInfo": "",
    "TargetLinkedLogonId": "",
    "TargetLogonGuid": "",
    "TargetLogonId": "",
    "TargetOutboundDomainName": "",
    "TargetOutboundUserName": "",
    "TargetServerName": "",
    "TargetSid": "",
    "TargetUser": "",
    "TargetUserName": "",
    "TargetUserSid": "",
    "TemplateContent": "",
    "TemplateDSObjectFQDN": "",
    "TemplateInternalName": "",
    "TemplateOID": "",
    "TemplateSchemaVersion": "",
    "TemplateVersion": "",
    "TokenElevationType": "",
    "TransmittedServices": "",
    "UserAccountControl": "",
    "UserParameters": "",
    "UserPrincipalName": "",
    "UserWorkstations": "",
    "VirtualAccount": "",
    "VendorIds": "",
    "Workstation": "",
    "WorkstationName": "",
    "PartitionKey": "",
    "RowKey": "",
    "StorageAccount": "",
    "AzureDeploymentID": "",
    "AzureTableName": "",
    "Type": "SecurityEvent",
    "_ResourceId": "/subscriptions/00000000-0000-0000-0000-000000000000/resourcegroups/soc-arc/providers/microsoft.hybridcompute/machines/ec2amaz-hk672qp"
  }
]